node-1.2.2-py3.9-nspkg.pth
node/base.py
node/compat.py
node/events.py
node/interfaces.py
node/locking.py
node/serializer.py
node/utils.py
node/behaviors/__init__.py
node/behaviors/adopt.py
node/behaviors/alias.py
node/behaviors/attributes.py
node/behaviors/cache.py
node/behaviors/common.py
node/behaviors/constraints.py
node/behaviors/context.py
node/behaviors/events.py
node/behaviors/factories.py
node/behaviors/fallback.py
node/behaviors/filter.py
node/behaviors/lifecycle.py
node/behaviors/mapping.py
node/behaviors/node.py
node/behaviors/nodespace.py
node/behaviors/order.py
node/behaviors/reference.py
node/behaviors/schema.py
node/behaviors/sequence.py
node/behaviors/storage.py
node/schema/__init__.py
node/schema/fields.py
node/schema/scope.py
node/schema/serializer.py
node/testing/__init__.py
node/testing/base.py
node/testing/env.py
node/testing/fullmapping.py
node/testing/profiling.py
node/tests/__init__.py
node/tests/test_adopt.py
node/tests/test_alias.py
node/tests/test_attributes.py
node/tests/test_base.py
node/tests/test_cache.py
node/tests/test_common.py
node/tests/test_constraints.py
node/tests/test_context.py
node/tests/test_events.py
node/tests/test_factories.py
node/tests/test_fallback.py
node/tests/test_filter.py
node/tests/test_lifecycle.py
node/tests/test_locking.py
node/tests/test_mapping.py
node/tests/test_node.py
node/tests/test_nodespace.py
node/tests/test_order.py
node/tests/test_reference.py
node/tests/test_schema.py
node/tests/test_sequence.py
node/tests/test_serializer.py
node/tests/test_storage.py
node/tests/test_testing.py
node/tests/test_tests.py
node/tests/test_utils.py
node-1.2.2.dist-info/LICENSE.rst
node-1.2.2.dist-info/METADATA
node-1.2.2.dist-info/WHEEL
node-1.2.2.dist-info/namespace_packages.txt
node-1.2.2.dist-info/top_level.txt
node-1.2.2.dist-info/zip-safe
node-1.2.2.dist-info/RECORD
