Metadata-Version: 2.1
Name: node
Version: 1.2.2
Summary: Building data structures as node trees
Home-page: http://github.com/conestack/node
Author: Node Contributors
Author-email: dev@conestack.org
License: Simplified BSD
Keywords: node tree fullmapping dict
Classifier: Development Status :: 5 - Production/Stable
Classifier: License :: OSI Approved :: BSD License
Classifier: Intended Audience :: Developers
Classifier: Operating System :: OS Independent
Classifier: Topic :: Software Development
Classifier: Programming Language :: Python
Classifier: Programming Language :: Python :: 2.7
Classifier: Programming Language :: Python :: 3.7
Classifier: Programming Language :: Python :: 3.8
Classifier: Programming Language :: Python :: 3.9
Classifier: Programming Language :: Python :: 3.10
License-File: LICENSE.rst
Requires-Dist: odict>=1.9.0
Requires-Dist: plumber>=1.5
Requires-Dist: setuptools
Requires-Dist: zope.component
Requires-Dist: zope.deferredimport
Requires-Dist: zope.deprecation
Requires-Dist: zope.lifecycleevent
